PyCPPExecuter/CPPExecuter.py
PyCPPExecuter/__init__.py
PyCPPExecuter/__version__.py
PyCPPExecuter/compiler_install.py
PyCPPExecuter-1.0.0.dist-info/LICENSE
PyCPPExecuter-1.0.0.dist-info/METADATA
PyCPPExecuter-1.0.0.dist-info/WHEEL
PyCPPExecuter-1.0.0.dist-info/entry_points.txt
PyCPPExecuter-1.0.0.dist-info/top_level.txt
PyCPPExecuter-1.0.0.dist-info/RECORD
