Metadata-Version: 2.1
Name: PyCPPExecuter
Version: 1.0.0
Summary: This is a module that uses python interface to execute the c/c++ programs and perform actions
Home-page: https://github.com/Jayakrishna112/PyCPPExecuter
Author: JayaKrishna
Author-email: jayakrishnamarni1234@gmail.com
License: MIT
Requires-Python: >=3.10
License-File: LICENSE
Provides-Extra: dev
Requires-Dist: pytest >=7.0 ; extra == 'dev'
Requires-Dist: twine >=4.0 ; extra == 'dev'
